{
    "version": "0.1",
    "components": [
        {
            "type": "rect",
            "position": {
                "x": 236.22,
                "y": -566.929
            },
            "stroke": {
                "width": "2pt"
            },
            "size": {
                "x": 1511.811,
                "y": 1285.039
            }
        },
        {
            "type": "rect",
            "position": {
                "x": 831.496,
                "y": -604.724
            },
            "size": {
                "x": 75.591,
                "y": 113.386
            }
        },
        {
            "type": "wire",
            "points": [
                {
                    "x": 755.905,
                    "y": -623.622
                },
                {
                    "x": 793.7,
                    "y": -623.622
                }
            ],
            "stroke": {
                "width": "0.4pt"
            },
            "directions": [
                "--"
            ]
        },
        {
            "type": "wire",
            "points": [
                {
                    "x": 869.291,
                    "y": -604.724
                },
                {
                    "x": 907.086,
                    "y": -604.724
                }
            ],
            "stroke": {
                "width": "0.4pt"
            },
            "directions": [
                "--"
            ]
        },
        {
            "type": "wire",
            "points": [
                {
                    "x": 793.7,
                    "y": -585.827
                },
                {
                    "x": 755.905,
                    "y": -585.827
                }
            ],
            "stroke": {
                "width": "0.4pt"
            },
            "directions": [
                "--"
            ]
        },
        {
            "type": "rect",
            "position": {
                "x": 831.496,
                "y": -623.622
            },
            "stroke": {
                "opacity": 0
            },
            "size": {
                "x": 75.591,
                "y": 37.795
            },
            "text": {
                "text": "in",
                "justify": 0,
                "fontSize": "small",
                "showPlaceholderText": true
            }
        },
        {
            "type": "rect",
            "position": {
                "x": 831.496,
                "y": -604.724
            },
            "stroke": {
                "opacity": 0
            },
            "size": {
                "x": 75.591,
                "y": 37.795
            },
            "text": {
                "text": "out",
                "align": 2,
                "justify": 0,
                "fontSize": "small",
                "showPlaceholderText": true
            }
        },
        {
            "type": "rect",
            "position": {
                "x": 831.496,
                "y": -585.827
            },
            "stroke": {
                "opacity": 0
            },
            "size": {
                "x": 75.591,
                "y": 37.795
            },
            "text": {
                "text": "write_en",
                "justify": 0,
                "fontSize": "small",
                "showPlaceholderText": true
            }
        },
        {
            "type": "rect",
            "position": {
                "x": 831.496,
                "y": -680.315
            },
            "stroke": {
                "opacity": 0
            },
            "size": {
                "x": 75.591,
                "y": 37.795
            },
            "text": {
                "text": "Instruction\nRegister",
                "align": 1,
                "justify": 0,
                "fontSize": "large",
                "showPlaceholderText": true
            }
        },
        {
            "type": "rect",
            "position": {
                "x": 831.496,
                "y": -226.772
            },
            "size": {
                "x": 75.591,
                "y": 113.386
            }
        },
        {
            "type": "wire",
            "points": [
                {
                    "x": 755.905,
                    "y": -245.669
                },
                {
                    "x": 793.701,
                    "y": -245.669
                }
            ],
            "stroke": {
                "width": "0.4pt"
            },
            "directions": [
                "--"
            ]
        },
        {
            "type": "wire",
            "points": [
                {
                    "x": 869.291,
                    "y": -226.772
                },
                {
                    "x": 907.086,
                    "y": -226.772
                }
            ],
            "stroke": {
                "width": "0.4pt"
            },
            "directions": [
                "--"
            ]
        },
        {
            "type": "wire",
            "points": [
                {
                    "x": 793.701,
                    "y": -207.874
                },
                {
                    "x": 755.905,
                    "y": -207.874
                }
            ],
            "stroke": {
                "width": "0.4pt"
            },
            "directions": [
                "--"
            ]
        },
        {
            "type": "rect",
            "position": {
                "x": 831.496,
                "y": -245.669
            },
            "stroke": {
                "opacity": 0
            },
            "size": {
                "x": 75.591,
                "y": 37.795
            },
            "text": {
                "text": "in",
                "justify": 0,
                "fontSize": "small",
                "showPlaceholderText": true
            }
        },
        {
            "type": "rect",
            "position": {
                "x": 831.496,
                "y": -226.772
            },
            "stroke": {
                "opacity": 0
            },
            "size": {
                "x": 75.591,
                "y": 37.795
            },
            "text": {
                "text": "out",
                "align": 2,
                "justify": 0,
                "fontSize": "small",
                "showPlaceholderText": true
            }
        },
        {
            "type": "rect",
            "position": {
                "x": 831.496,
                "y": -207.874
            },
            "stroke": {
                "opacity": 0
            },
            "size": {
                "x": 75.591,
                "y": 37.795
            },
            "text": {
                "text": "write_en",
                "justify": 0,
                "fontSize": "small",
                "showPlaceholderText": true
            }
        },
        {
            "type": "rect",
            "position": {
                "x": 831.496,
                "y": -302.362
            },
            "stroke": {
                "opacity": 0
            },
            "size": {
                "x": 75.591,
                "y": 37.795
            },
            "text": {
                "text": "MDR\nRegister",
                "align": 1,
                "justify": 0,
                "fontSize": "large",
                "showPlaceholderText": true
            }
        },
        {
            "type": "rect",
            "position": {
                "x": 831.496,
                "y": -415.748
            },
            "size": {
                "x": 75.591,
                "y": 113.386
            }
        },
        {
            "type": "wire",
            "points": [
                {
                    "x": 755.905,
                    "y": -434.645
                },
                {
                    "x": 793.701,
                    "y": -434.645
                }
            ],
            "stroke": {
                "width": "0.4pt"
            },
            "directions": [
                "--"
            ]
        },
        {
            "type": "wire",
            "points": [
                {
                    "x": 869.291,
                    "y": -415.748
                },
                {
                    "x": 907.086,
                    "y": -415.748
                }
            ],
            "stroke": {
                "width": "0.4pt"
            },
            "directions": [
                "--"
            ]
        },
        {
            "type": "wire",
            "points": [
                {
                    "x": 793.701,
                    "y": -396.85
                },
                {
                    "x": 755.905,
                    "y": -396.85
                }
            ],
            "stroke": {
                "width": "0.4pt"
            },
            "directions": [
                "--"
            ]
        },
        {
            "type": "rect",
            "position": {
                "x": 831.496,
                "y": -434.645
            },
            "stroke": {
                "opacity": 0
            },
            "size": {
                "x": 75.591,
                "y": 37.795
            },
            "text": {
                "text": "in",
                "justify": 0,
                "fontSize": "small",
                "showPlaceholderText": true
            }
        },
        {
            "type": "rect",
            "position": {
                "x": 831.496,
                "y": -415.748
            },
            "stroke": {
                "opacity": 0
            },
            "size": {
                "x": 75.591,
                "y": 37.795
            },
            "text": {
                "text": "out",
                "align": 2,
                "justify": 0,
                "fontSize": "small",
                "showPlaceholderText": true
            }
        },
        {
            "type": "rect",
            "position": {
                "x": 831.496,
                "y": -396.85
            },
            "stroke": {
                "opacity": 0
            },
            "size": {
                "x": 75.591,
                "y": 37.795
            },
            "text": {
                "text": "write_en",
                "justify": 0,
                "fontSize": "small",
                "showPlaceholderText": true
            }
        },
        {
            "type": "rect",
            "position": {
                "x": 831.496,
                "y": -491.338
            },
            "stroke": {
                "opacity": 0
            },
            "size": {
                "x": 75.591,
                "y": 37.795
            },
            "text": {
                "text": "Operand\nRegister",
                "align": 1,
                "justify": 0,
                "fontSize": "large",
                "showPlaceholderText": true
            }
        },
        {
            "type": "rect",
            "position": {
                "x": 302.362,
                "y": -963.78
            },
            "size": {
                "x": 75.591,
                "y": 113.386
            }
        },
        {
            "type": "wire",
            "points": [
                {
                    "x": 226.771,
                    "y": -982.677
                },
                {
                    "x": 264.567,
                    "y": -982.677
                }
            ],
            "stroke": {
                "width": "0.4pt"
            },
            "directions": [
                "--"
            ]
        },
        {
            "type": "wire",
            "points": [
                {
                    "x": 340.157,
                    "y": -963.78
                },
                {
                    "x": 377.952,
                    "y": -963.78
                }
            ],
            "stroke": {
                "width": "0.4pt"
            },
            "directions": [
                "--"
            ]
        },
        {
            "type": "wire",
            "points": [
                {
                    "x": 264.567,
                    "y": -944.882
                },
                {
                    "x": 226.771,
                    "y": -944.882
                }
            ],
            "stroke": {
                "width": "0.4pt"
            },
            "directions": [
                "--"
            ]
        },
        {
            "type": "rect",
            "position": {
                "x": 302.362,
                "y": -982.677
            },
            "stroke": {
                "opacity": 0
            },
            "size": {
                "x": 75.591,
                "y": 37.795
            },
            "text": {
                "text": "in",
                "justify": 0,
                "fontSize": "small",
                "showPlaceholderText": true
            }
        },
        {
            "type": "rect",
            "position": {
                "x": 302.362,
                "y": -963.78
            },
            "stroke": {
                "opacity": 0
            },
            "size": {
                "x": 75.591,
                "y": 37.795
            },
            "text": {
                "text": "out",
                "align": 2,
                "justify": 0,
                "fontSize": "small",
                "showPlaceholderText": true
            }
        },
        {
            "type": "rect",
            "position": {
                "x": 302.362,
                "y": -944.882
            },
            "stroke": {
                "opacity": 0
            },
            "size": {
                "x": 75.591,
                "y": 37.795
            },
            "text": {
                "text": "write_en",
                "justify": 0,
                "fontSize": "small",
                "showPlaceholderText": true
            }
        },
        {
            "type": "rect",
            "position": {
                "x": 302.362,
                "y": -1039.37
            },
            "stroke": {
                "opacity": 0
            },
            "size": {
                "x": 75.591,
                "y": 37.795
            },
            "text": {
                "text": "IN\nRegister",
                "align": 1,
                "justify": 0,
                "fontSize": "large",
                "showPlaceholderText": true
            }
        },
        {
            "type": "rect",
            "position": {
                "x": 529.134,
                "y": -963.78
            },
            "size": {
                "x": 75.591,
                "y": 113.386
            }
        },
        {
            "type": "wire",
            "points": [
                {
                    "x": 453.543,
                    "y": -982.677
                },
                {
                    "x": 491.339,
                    "y": -982.677
                }
            ],
            "stroke": {
                "width": "0.4pt"
            },
            "directions": [
                "--"
            ]
        },
        {
            "type": "wire",
            "points": [
                {
                    "x": 566.929,
                    "y": -963.78
                },
                {
                    "x": 604.724,
                    "y": -963.78
                }
            ],
            "stroke": {
                "width": "0.4pt"
            },
            "directions": [
                "--"
            ]
        },
        {
            "type": "wire",
            "points": [
                {
                    "x": 491.339,
                    "y": -944.882
                },
                {
                    "x": 453.543,
                    "y": -944.882
                }
            ],
            "stroke": {
                "width": "0.4pt"
            },
            "directions": [
                "--"
            ]
        },
        {
            "type": "rect",
            "position": {
                "x": 529.134,
                "y": -982.677
            },
            "stroke": {
                "opacity": 0
            },
            "size": {
                "x": 75.591,
                "y": 37.795
            },
            "text": {
                "text": "in",
                "justify": 0,
                "fontSize": "small",
                "showPlaceholderText": true
            }
        },
        {
            "type": "rect",
            "position": {
                "x": 529.134,
                "y": -963.78
            },
            "stroke": {
                "opacity": 0
            },
            "size": {
                "x": 75.591,
                "y": 37.795
            },
            "text": {
                "text": "out",
                "align": 2,
                "justify": 0,
                "fontSize": "small",
                "showPlaceholderText": true
            }
        },
        {
            "type": "rect",
            "position": {
                "x": 529.134,
                "y": -944.882
            },
            "stroke": {
                "opacity": 0
            },
            "size": {
                "x": 75.591,
                "y": 37.795
            },
            "text": {
                "text": "write_en",
                "justify": 0,
                "fontSize": "small",
                "showPlaceholderText": true
            }
        },
        {
            "type": "rect",
            "position": {
                "x": 529.134,
                "y": -1039.37
            },
            "stroke": {
                "opacity": 0
            },
            "size": {
                "x": 75.591,
                "y": 37.795
            },
            "text": {
                "text": "OUT\nRegister",
                "align": 1,
                "justify": 0,
                "fontSize": "large",
                "showPlaceholderText": true
            }
        },
        {
            "type": "rect",
            "position": {
                "x": -18.898,
                "y": -812.598
            },
            "size": {
                "x": 113.386,
                "y": 151.181
            }
        },
        {
            "type": "rect",
            "position": {
                "x": -37.795,
                "y": -869.29
            },
            "stroke": {
                "opacity": 0
            },
            "size": {
                "x": 75.591,
                "y": 37.795
            },
            "text": {
                "text": "read_en",
                "justify": 0,
                "showPlaceholderText": true
            }
        },
        {
            "type": "rect",
            "position": {
                "x": -37.795,
                "y": -850.393
            },
            "stroke": {
                "opacity": 0
            },
            "size": {
                "x": 75.591,
                "y": 37.795
            },
            "text": {
                "text": "write_en",
                "justify": 0,
                "showPlaceholderText": true
            }
        },
        {
            "type": "rect",
            "position": {
                "x": -37.795,
                "y": -774.802
            },
            "stroke": {
                "opacity": 0
            },
            "size": {
                "x": 75.591,
                "y": 37.795
            },
            "text": {
                "text": "data_i",
                "justify": 0,
                "showPlaceholderText": true
            }
        },
        {
            "type": "rect",
            "position": {
                "x": -37.795,
                "y": -755.905
            },
            "stroke": {
                "opacity": 0
            },
            "size": {
                "x": 75.591,
                "y": 37.795
            },
            "text": {
                "text": "addr_i",
                "justify": 0,
                "showPlaceholderText": true
            }
        },
        {
            "type": "rect",
            "position": {
                "x": 0,
                "y": -812.598
            },
            "stroke": {
                "opacity": 0
            },
            "size": {
                "x": 75.591,
                "y": 37.795
            },
            "text": {
                "text": "data_o",
                "align": 2,
                "justify": 0,
                "showPlaceholderText": true
            }
        },
        {
            "type": "rect",
            "position": {
                "x": -18.898,
                "y": -907.086
            },
            "stroke": {
                "opacity": 0
            },
            "size": {
                "x": 113.386,
                "y": 37.795
            },
            "text": {
                "text": "Register Memory",
                "align": 1,
                "justify": 0,
                "fontSize": "large",
                "showPlaceholderText": true
            }
        },
        {
            "type": "wire",
            "points": [
                {
                    "x": -75.591,
                    "y": -869.29
                },
                {
                    "x": -113.386,
                    "y": -869.29
                }
            ],
            "stroke": {
                "width": "0.4pt"
            },
            "directions": [
                "--"
            ]
        },
        {
            "type": "wire",
            "points": [
                {
                    "x": -75.591,
                    "y": -850.393
                },
                {
                    "x": -113.386,
                    "y": -850.393
                }
            ],
            "stroke": {
                "width": "0.4pt"
            },
            "directions": [
                "--"
            ]
        },
        {
            "type": "wire",
            "points": [
                {
                    "x": -75.591,
                    "y": -774.802
                },
                {
                    "x": -113.386,
                    "y": -774.802
                }
            ],
            "stroke": {
                "width": "0.4pt"
            },
            "directions": [
                "--"
            ]
        },
        {
            "type": "wire",
            "points": [
                {
                    "x": -75.591,
                    "y": -755.905
                },
                {
                    "x": -113.386,
                    "y": -755.905
                }
            ],
            "stroke": {
                "width": "0.4pt"
            },
            "directions": [
                "--"
            ]
        },
        {
            "type": "wire",
            "points": [
                {
                    "x": 37.795,
                    "y": -812.598
                },
                {
                    "x": 75.59,
                    "y": -812.598
                }
            ],
            "stroke": {
                "width": "0.4pt"
            },
            "directions": [
                "--"
            ]
        },
        {
            "type": "rect",
            "position": {
                "x": 831.496,
                "y": -793.701
            },
            "size": {
                "x": 75.591,
                "y": 113.386
            }
        },
        {
            "type": "wire",
            "points": [
                {
                    "x": 755.905,
                    "y": -812.599
                },
                {
                    "x": 793.7,
                    "y": -812.599
                }
            ],
            "stroke": {
                "width": "0.4pt"
            },
            "directions": [
                "--"
            ]
        },
        {
            "type": "wire",
            "points": [
                {
                    "x": 869.291,
                    "y": -793.701
                },
                {
                    "x": 907.086,
                    "y": -793.701
                }
            ],
            "stroke": {
                "width": "0.4pt"
            },
            "directions": [
                "--"
            ]
        },
        {
            "type": "wire",
            "points": [
                {
                    "x": 793.7,
                    "y": -774.804
                },
                {
                    "x": 755.905,
                    "y": -774.804
                }
            ],
            "stroke": {
                "width": "0.4pt"
            },
            "directions": [
                "--"
            ]
        },
        {
            "type": "rect",
            "position": {
                "x": 831.496,
                "y": -812.599
            },
            "stroke": {
                "opacity": 0
            },
            "size": {
                "x": 75.591,
                "y": 37.795
            },
            "text": {
                "text": "in",
                "justify": 0,
                "fontSize": "small",
                "showPlaceholderText": true
            }
        },
        {
            "type": "rect",
            "position": {
                "x": 831.496,
                "y": -793.701
            },
            "stroke": {
                "opacity": 0
            },
            "size": {
                "x": 75.591,
                "y": 37.795
            },
            "text": {
                "text": "out",
                "align": 2,
                "justify": 0,
                "fontSize": "small",
                "showPlaceholderText": true
            }
        },
        {
            "type": "rect",
            "position": {
                "x": 831.496,
                "y": -774.804
            },
            "stroke": {
                "opacity": 0
            },
            "size": {
                "x": 75.591,
                "y": 37.795
            },
            "text": {
                "text": "write_en",
                "justify": 0,
                "fontSize": "small",
                "showPlaceholderText": true
            }
        },
        {
            "type": "rect",
            "position": {
                "x": 831.496,
                "y": -869.292
            },
            "stroke": {
                "opacity": 0
            },
            "size": {
                "x": 75.591,
                "y": 37.795
            },
            "text": {
                "text": "Accumulator\nRegister",
                "align": 1,
                "justify": 0,
                "fontSize": "large",
                "showPlaceholderText": true
            }
        },
        {
            "type": "rect",
            "position": {
                "x": -18.898,
                "y": -548.031
            },
            "size": {
                "x": 113.386,
                "y": 151.181
            }
        },
        {
            "type": "rect",
            "position": {
                "x": -37.796,
                "y": -585.826
            },
            "stroke": {
                "opacity": 0
            },
            "size": {
                "x": 75.591,
                "y": 37.795
            },
            "text": {
                "text": "a_i",
                "justify": 0,
                "showPlaceholderText": true
            }
        },
        {
            "type": "rect",
            "position": {
                "x": -37.796,
                "y": -548.031
            },
            "stroke": {
                "opacity": 0
            },
            "size": {
                "x": 75.591,
                "y": 37.795
            },
            "text": {
                "text": "b_i",
                "justify": 0,
                "showPlaceholderText": true
            }
        },
        {
            "type": "rect",
            "position": {
                "x": -37.796,
                "y": -510.236
            },
            "stroke": {
                "opacity": 0
            },
            "size": {
                "x": 75.591,
                "y": 37.795
            },
            "text": {
                "text": "oc_i",
                "justify": 0,
                "showPlaceholderText": true
            }
        },
        {
            "type": "rect",
            "position": {
                "x": -0.001,
                "y": -585.826
            },
            "stroke": {
                "opacity": 0
            },
            "size": {
                "x": 75.591,
                "y": 37.795
            },
            "text": {
                "text": "result_o",
                "align": 2,
                "justify": 0,
                "showPlaceholderText": true
            }
        },
        {
            "type": "rect",
            "position": {
                "x": -18.898,
                "y": -642.519
            },
            "stroke": {
                "opacity": 0
            },
            "size": {
                "x": 113.386,
                "y": 37.795
            },
            "text": {
                "text": "ALU",
                "align": 1,
                "justify": 1,
                "fontSize": "large",
                "showPlaceholderText": true
            }
        },
        {
            "type": "wire",
            "points": [
                {
                    "x": -75.591,
                    "y": -585.826
                },
                {
                    "x": -113.386,
                    "y": -585.826
                }
            ],
            "stroke": {
                "width": "0.4pt"
            },
            "directions": [
                "--"
            ]
        },
        {
            "type": "wire",
            "points": [
                {
                    "x": -75.591,
                    "y": -548.031
                },
                {
                    "x": -113.386,
                    "y": -548.031
                }
            ],
            "stroke": {
                "width": "0.4pt"
            },
            "directions": [
                "--"
            ]
        },
        {
            "type": "wire",
            "points": [
                {
                    "x": -75.591,
                    "y": -510.236
                },
                {
                    "x": -113.386,
                    "y": -510.236
                }
            ],
            "stroke": {
                "width": "0.4pt"
            },
            "directions": [
                "--"
            ]
        },
        {
            "type": "wire",
            "points": [
                {
                    "x": 37.795,
                    "y": -585.826
                },
                {
                    "x": 75.59,
                    "y": -585.826
                }
            ],
            "stroke": {
                "width": "0.4pt"
            },
            "directions": [
                "--"
            ]
        },
        {
            "type": "rect",
            "position": {
                "x": -0.001,
                "y": -510.236
            },
            "stroke": {
                "opacity": 0
            },
            "size": {
                "x": 75.591,
                "y": 37.795
            },
            "text": {
                "text": "carry_o",
                "align": 2,
                "justify": 0,
                "showPlaceholderText": true
            }
        },
        {
            "type": "wire",
            "points": [
                {
                    "x": 37.795,
                    "y": -510.236
                },
                {
                    "x": 75.59,
                    "y": -510.236
                }
            ],
            "stroke": {
                "width": "0.4pt"
            },
            "directions": [
                "--"
            ]
        },
        {
            "type": "wire",
            "points": [
                {
                    "x": 718.11,
                    "y": -812.599
                },
                {
                    "x": 755.906,
                    "y": -812.599
                }
            ],
            "stroke": {
                "width": "0.4pt"
            },
            "directions": [
                "-|"
            ]
        },
        {
            "type": "wire",
            "points": [
                {
                    "x": 755.906,
                    "y": -774.804
                },
                {
                    "x": 718.11,
                    "y": -774.804
                }
            ],
            "stroke": {
                "width": "0.4pt"
            },
            "directions": [
                "-|"
            ]
        },
        {
            "type": "wire",
            "points": [
                {
                    "x": 755.906,
                    "y": -623.622
                },
                {
                    "x": 718.11,
                    "y": -623.622
                }
            ],
            "stroke": {
                "width": "0.4pt"
            },
            "directions": [
                "-|"
            ]
        },
        {
            "type": "rect",
            "position": {
                "x": -94.488,
                "y": -264.567
            },
            "size": {
                "x": 264.567,
                "y": 151.181
            }
        },
        {
            "type": "rect",
            "position": {
                "x": -94.488,
                "y": -359.056
            },
            "stroke": {
                "opacity": 0
            },
            "size": {
                "x": 264.567,
                "y": 37.795
            },
            "text": {
                "text": "Programmer",
                "align": 1,
                "justify": 1,
                "fontSize": "large",
                "showPlaceholderText": true
            }
        },
        {
            "type": "rect",
            "position": {
                "x": -188.976,
                "y": -226.772
            },
            "stroke": {
                "opacity": 0
            },
            "size": {
                "x": 75.591,
                "y": 37.795
            },
            "text": {
                "text": "active_i",
                "justify": 0,
                "showPlaceholderText": true
            }
        },
        {
            "type": "rect",
            "position": {
                "x": -170.079,
                "y": -302.362
            },
            "stroke": {
                "opacity": 0
            },
            "size": {
                "x": 113.386,
                "y": 37.795
            },
            "text": {
                "text": "uart_data_i",
                "justify": 0,
                "showPlaceholderText": true
            }
        },
        {
            "type": "rect",
            "position": {
                "x": -151.181,
                "y": -264.567
            },
            "stroke": {
                "opacity": 0
            },
            "size": {
                "x": 151.181,
                "y": 37.795
            },
            "text": {
                "text": "data_valid_strb_i",
                "justify": 0,
                "showPlaceholderText": true
            }
        },
        {
            "type": "rect",
            "position": {
                "x": -37.795,
                "y": -302.363
            },
            "stroke": {
                "opacity": 0
            },
            "size": {
                "x": 151.181,
                "y": 37.795
            },
            "text": {
                "text": "addr_o",
                "align": 2,
                "justify": 0,
                "showPlaceholderText": true
            }
        },
        {
            "type": "rect",
            "position": {
                "x": -37.795,
                "y": -264.568
            },
            "stroke": {
                "opacity": 0
            },
            "size": {
                "x": 151.181,
                "y": 37.795
            },
            "text": {
                "text": "data_o",
                "align": 2,
                "justify": 0,
                "showPlaceholderText": true
            }
        },
        {
            "type": "rect",
            "position": {
                "x": -37.795,
                "y": -226.772
            },
            "stroke": {
                "opacity": 0
            },
            "size": {
                "x": 151.181,
                "y": 37.795
            },
            "text": {
                "text": "enable_write_o",
                "align": 2,
                "justify": 0,
                "showPlaceholderText": true
            }
        },
        {
            "type": "wire",
            "points": [
                {
                    "x": 37.796,
                    "y": -302.363
                },
                {
                    "x": 75.591,
                    "y": -302.363
                }
            ],
            "stroke": {
                "width": "0.4pt"
            },
            "directions": [
                "--"
            ]
        },
        {
            "type": "wire",
            "points": [
                {
                    "x": 37.796,
                    "y": -264.567
                },
                {
                    "x": 75.591,
                    "y": -264.567
                }
            ],
            "stroke": {
                "width": "0.4pt"
            },
            "directions": [
                "--"
            ]
        },
        {
            "type": "wire",
            "points": [
                {
                    "x": 37.796,
                    "y": -226.772
                },
                {
                    "x": 75.591,
                    "y": -226.772
                }
            ],
            "stroke": {
                "width": "0.4pt"
            },
            "directions": [
                "--"
            ]
        },
        {
            "type": "wire",
            "points": [
                {
                    "x": -226.771,
                    "y": -302.363
                },
                {
                    "x": -264.567,
                    "y": -302.363
                }
            ],
            "stroke": {
                "width": "0.4pt"
            },
            "directions": [
                "--"
            ]
        },
        {
            "type": "wire",
            "points": [
                {
                    "x": -226.771,
                    "y": -264.567
                },
                {
                    "x": -264.567,
                    "y": -264.567
                }
            ],
            "stroke": {
                "width": "0.4pt"
            },
            "directions": [
                "--"
            ]
        },
        {
            "type": "wire",
            "points": [
                {
                    "x": -226.771,
                    "y": -226.772
                },
                {
                    "x": -264.567,
                    "y": -226.772
                }
            ],
            "stroke": {
                "width": "0.4pt"
            },
            "directions": [
                "--"
            ]
        },
        {
            "type": "rect",
            "position": {
                "x": -396.85,
                "y": -283.465
            },
            "size": {
                "x": 188.976,
                "y": 113.386
            }
        },
        {
            "type": "rect",
            "position": {
                "x": -396.85,
                "y": -359.056
            },
            "stroke": {
                "opacity": 0
            },
            "size": {
                "x": 188.976,
                "y": 37.795
            },
            "text": {
                "text": "Uart_RX",
                "align": 1,
                "justify": 1,
                "fontSize": "large",
                "showPlaceholderText": true
            }
        },
        {
            "type": "rect",
            "position": {
                "x": -434.645,
                "y": -283.465
            },
            "stroke": {
                "opacity": 0
            },
            "size": {
                "x": 113.386,
                "y": 37.795
            },
            "text": {
                "text": "rx_i",
                "justify": 0,
                "showPlaceholderText": true
            }
        },
        {
            "type": "rect",
            "position": {
                "x": -359.054,
                "y": -302.363
            },
            "stroke": {
                "opacity": 0
            },
            "size": {
                "x": 113.386,
                "y": 37.795
            },
            "text": {
                "text": "data_o",
                "align": 2,
                "justify": 0,
                "showPlaceholderText": true
            }
        },
        {
            "type": "rect",
            "position": {
                "x": -359.054,
                "y": -264.568
            },
            "stroke": {
                "opacity": 0
            },
            "size": {
                "x": 113.386,
                "y": 37.795
            },
            "text": {
                "text": "data_valid_strb_o",
                "align": 2,
                "justify": 0,
                "showPlaceholderText": true
            }
        },
        {
            "type": "wire",
            "points": [
                {
                    "x": -302.361,
                    "y": -302.363
                },
                {
                    "x": -264.566,
                    "y": -302.363
                }
            ],
            "stroke": {
                "width": "0.4pt"
            },
            "directions": [
                "--"
            ]
        },
        {
            "type": "wire",
            "points": [
                {
                    "x": -302.361,
                    "y": -264.568
                },
                {
                    "x": -264.566,
                    "y": -264.568
                }
            ],
            "stroke": {
                "width": "0.4pt"
            },
            "directions": [
                "--"
            ]
        },
        {
            "type": "wire",
            "points": [
                {
                    "x": -500.787,
                    "y": -283.465
                },
                {
                    "x": -491.338,
                    "y": -283.465
                }
            ],
            "stroke": {
                "width": "0.4pt"
            },
            "directions": [
                "--"
            ]
        },
        {
            "type": "wire",
            "points": [
                {
                    "x": -500.787,
                    "y": -283.465
                },
                {
                    "x": -529.133,
                    "y": -283.465
                }
            ],
            "stroke": {
                "width": "0.4pt"
            },
            "directions": [
                "--"
            ]
        },
        {
            "type": "wire",
            "points": [
                {
                    "x": 907.087,
                    "y": -793.701
                },
                {
                    "x": 907.087,
                    "y": -718.111
                },
                {
                    "x": 718.11,
                    "y": -718.111
                }
            ],
            "stroke": {
                "width": "0.4pt"
            },
            "directions": [
                null,
                "-|"
            ]
        },
        {
            "type": "wire",
            "points": [
                {
                    "x": 755.906,
                    "y": -585.826
                },
                {
                    "x": 718.11,
                    "y": -585.826
                }
            ],
            "stroke": {
                "width": "0.4pt"
            },
            "directions": [
                null
            ]
        },
        {
            "type": "wire",
            "points": [
                {
                    "x": 907.087,
                    "y": -604.724
                },
                {
                    "x": 907.087,
                    "y": -529.133
                },
                {
                    "x": 718.11,
                    "y": -529.133
                }
            ],
            "stroke": {
                "width": "0.4pt"
            },
            "directions": [
                null,
                "-|"
            ]
        },
        {
            "type": "wire",
            "points": [
                {
                    "x": 755.906,
                    "y": -434.645
                },
                {
                    "x": 718.11,
                    "y": -434.645
                }
            ],
            "stroke": {
                "width": "0.4pt"
            },
            "directions": [
                "-|"
            ]
        },
        {
            "type": "wire",
            "points": [
                {
                    "x": 755.906,
                    "y": -396.85
                },
                {
                    "x": 718.11,
                    "y": -396.85
                }
            ],
            "stroke": {
                "width": "0.4pt"
            },
            "directions": [
                "-|"
            ]
        },
        {
            "type": "wire",
            "points": [
                {
                    "x": 907.087,
                    "y": -415.748
                },
                {
                    "x": 907.087,
                    "y": -340.157
                },
                {
                    "x": 718.11,
                    "y": -340.157
                }
            ],
            "stroke": {
                "width": "0.4pt"
            },
            "directions": [
                null,
                "-|"
            ]
        },
        {
            "type": "wire",
            "points": [
                {
                    "x": 755.906,
                    "y": -245.67
                },
                {
                    "x": 718.11,
                    "y": -245.67
                }
            ],
            "stroke": {
                "width": "0.4pt"
            },
            "directions": [
                null
            ]
        },
        {
            "type": "wire",
            "points": [
                {
                    "x": 755.906,
                    "y": -207.875
                },
                {
                    "x": 718.11,
                    "y": -207.875
                }
            ],
            "stroke": {
                "width": "0.4pt"
            },
            "directions": [
                "-|"
            ]
        },
        {
            "type": "wire",
            "points": [
                {
                    "x": 907.087,
                    "y": -226.772
                },
                {
                    "x": 907.087,
                    "y": -151.182
                },
                {
                    "x": 718.11,
                    "y": -151.182
                }
            ],
            "stroke": {
                "width": "0.4pt"
            },
            "directions": [
                "-|",
                "-|"
            ]
        },
        {
            "type": "wire",
            "points": [
                {
                    "x": 453.543,
                    "y": -944.882
                },
                {
                    "x": 453.543,
                    "y": -869.291
                }
            ],
            "stroke": {
                "width": "0.4pt"
            },
            "directions": [
                "-|"
            ]
        },
        {
            "type": "wire",
            "points": [
                {
                    "x": 453.543,
                    "y": -982.677
                },
                {
                    "x": 434.646,
                    "y": -982.677
                },
                {
                    "x": 434.646,
                    "y": -869.291
                }
            ],
            "stroke": {
                "width": "0.4pt"
            },
            "directions": [
                "-|",
                null
            ]
        },
        {
            "type": "wire",
            "points": [
                {
                    "x": 226.772,
                    "y": -944.882
                },
                {
                    "x": 226.772,
                    "y": -869.291
                }
            ],
            "stroke": {
                "width": "0.4pt"
            },
            "directions": [
                null
            ]
        },
        {
            "type": "wire",
            "points": [
                {
                    "x": 226.772,
                    "y": -982.677
                },
                {
                    "x": 207.874,
                    "y": -982.677
                },
                {
                    "x": 207.874,
                    "y": -869.291
                }
            ],
            "stroke": {
                "width": "0.4pt"
            },
            "directions": [
                "-|",
                "|-"
            ]
        },
        {
            "type": "wire",
            "points": [
                {
                    "x": 75.591,
                    "y": -812.598
                },
                {
                    "x": 151.181,
                    "y": -812.598
                }
            ],
            "stroke": {
                "width": "0.4pt"
            },
            "directions": [
                "-|"
            ]
        },
        {
            "type": "wire",
            "points": [
                {
                    "x": -113.386,
                    "y": -755.905
                },
                {
                    "x": -113.386,
                    "y": -718.11
                },
                {
                    "x": 151.181,
                    "y": -718.11
                }
            ],
            "stroke": {
                "width": "0.4pt"
            },
            "directions": [
                "-|",
                "-|"
            ]
        },
        {
            "type": "wire",
            "points": [
                {
                    "x": -113.386,
                    "y": -774.803
                },
                {
                    "x": -132.283,
                    "y": -774.803
                },
                {
                    "x": -132.283,
                    "y": -699.212
                },
                {
                    "x": 151.181,
                    "y": -699.212
                }
            ],
            "stroke": {
                "width": "0.4pt"
            },
            "directions": [
                "-|",
                null,
                null
            ]
        },
        {
            "type": "wire",
            "points": [
                {
                    "x": -113.386,
                    "y": -850.393
                },
                {
                    "x": -151.181,
                    "y": -850.393
                },
                {
                    "x": -151.181,
                    "y": -680.315
                },
                {
                    "x": 151.181,
                    "y": -680.315
                }
            ],
            "stroke": {
                "width": "0.4pt"
            },
            "directions": [
                "-|",
                "-|",
                "-|"
            ]
        },
        {
            "type": "wire",
            "points": [
                {
                    "x": -113.386,
                    "y": -869.291
                },
                {
                    "x": -160.63,
                    "y": -869.291
                },
                {
                    "x": -170.079,
                    "y": -869.291
                },
                {
                    "x": -170.079,
                    "y": -661.417
                },
                {
                    "x": 151.181,
                    "y": -661.417
                }
            ],
            "stroke": {
                "width": "0.4pt"
            },
            "directions": [
                "-|",
                "|-",
                "|-",
                "-|"
            ]
        },
        {
            "type": "wire",
            "points": [
                {
                    "x": 75.591,
                    "y": -585.826
                },
                {
                    "x": 151.181,
                    "y": -585.826
                }
            ],
            "stroke": {
                "width": "0.4pt"
            },
            "directions": [
                "-|"
            ]
        },
        {
            "type": "wire",
            "points": [
                {
                    "x": 75.591,
                    "y": -510.236
                },
                {
                    "x": 151.181,
                    "y": -510.236
                }
            ],
            "stroke": {
                "width": "0.4pt"
            },
            "directions": [
                "-|"
            ]
        },
        {
            "type": "wire",
            "points": [
                {
                    "x": -113.386,
                    "y": -510.236
                },
                {
                    "x": -113.386,
                    "y": -453.543
                },
                {
                    "x": 151.181,
                    "y": -453.543
                }
            ],
            "stroke": {
                "width": "0.4pt"
            },
            "directions": [
                "-|",
                "-|"
            ]
        },
        {
            "type": "wire",
            "points": [
                {
                    "x": -113.386,
                    "y": -548.031
                },
                {
                    "x": -132.283,
                    "y": -548.031
                },
                {
                    "x": -132.283,
                    "y": -434.645
                },
                {
                    "x": 151.181,
                    "y": -434.645
                }
            ],
            "stroke": {
                "width": "0.4pt"
            },
            "directions": [
                "-|",
                "-|",
                "-|"
            ]
        },
        {
            "type": "wire",
            "points": [
                {
                    "x": -113.385,
                    "y": -585.827
                },
                {
                    "x": -151.18,
                    "y": -585.827
                },
                {
                    "x": -151.18,
                    "y": -415.749
                },
                {
                    "x": 151.182,
                    "y": -415.749
                }
            ],
            "stroke": {
                "width": "0.4pt"
            },
            "directions": [
                "-|",
                "-|",
                "-|"
            ]
        },
        {
            "type": "wire",
            "points": [
                {
                    "x": 75.591,
                    "y": -226.772
                },
                {
                    "x": 151.181,
                    "y": -226.772
                }
            ],
            "stroke": {
                "width": "0.4pt"
            },
            "directions": [
                "-|"
            ]
        },
        {
            "type": "wire",
            "points": [
                {
                    "x": 75.591,
                    "y": -302.362
                },
                {
                    "x": 151.181,
                    "y": -302.362
                }
            ],
            "stroke": {
                "width": "0.4pt"
            },
            "directions": [
                "-|"
            ]
        },
        {
            "type": "wire",
            "points": [
                {
                    "x": 75.591,
                    "y": -264.567
                },
                {
                    "x": 151.181,
                    "y": -264.567
                }
            ],
            "stroke": {
                "width": "0.4pt"
            },
            "directions": [
                "-|"
            ]
        },
        {
            "type": "wire",
            "points": [
                {
                    "x": -264.567,
                    "y": -226.772
                },
                {
                    "x": 151.181,
                    "y": -151.181
                }
            ],
            "stroke": {
                "width": "0.4pt"
            },
            "directions": [
                "|-"
            ]
        },
        {
            "type": "wire",
            "points": [
                {
                    "x": -529.134,
                    "y": -283.465
                },
                {
                    "x": -604.724,
                    "y": -283.465
                }
            ],
            "stroke": {
                "width": "0.4pt"
            },
            "directions": [
                null
            ]
        },
        {
            "type": "wire",
            "points": [
                {
                    "x": 377.953,
                    "y": -963.78
                },
                {
                    "x": 377.953,
                    "y": -1133.858
                },
                {
                    "x": -604.724,
                    "y": -1133.858
                }
            ],
            "stroke": {
                "width": "0.4pt"
            },
            "directions": [
                null,
                "-|"
            ]
        },
        {
            "type": "wire",
            "points": [
                {
                    "x": 462.992,
                    "y": -113.386
                },
                {
                    "x": 462.992,
                    "y": -75.591
                },
                {
                    "x": 982.677,
                    "y": -75.591
                }
            ],
            "stroke": {
                "width": "0.4pt"
            },
            "directions": [
                null,
                "-|"
            ]
        },
        {
            "type": "wire",
            "points": [
                {
                    "x": 444.094,
                    "y": -113.386
                },
                {
                    "x": 444.094,
                    "y": -56.693
                },
                {
                    "x": 982.677,
                    "y": -56.693
                }
            ],
            "stroke": {
                "width": "0.4pt"
            },
            "directions": [
                null,
                "-|"
            ]
        },
        {
            "type": "wire",
            "points": [
                {
                    "x": 425.197,
                    "y": -113.386
                },
                {
                    "x": 425.197,
                    "y": -37.795
                },
                {
                    "x": 982.677,
                    "y": -37.795
                }
            ],
            "stroke": {
                "width": "0.4pt"
            },
            "directions": [
                null,
                "-|"
            ]
        },
        {
            "type": "wire",
            "points": [
                {
                    "x": 406.299,
                    "y": -113.386
                },
                {
                    "x": 406.299,
                    "y": -18.898
                },
                {
                    "x": 982.677,
                    "y": -18.898
                }
            ],
            "stroke": {
                "width": "0.4pt"
            },
            "directions": [
                "|-",
                "-|"
            ]
        },
        {
            "type": "wire",
            "points": [
                {
                    "x": 387.401,
                    "y": -113.386
                },
                {
                    "x": 387.401,
                    "y": 0
                },
                {
                    "x": 982.677,
                    "y": 0
                }
            ],
            "stroke": {
                "width": "0.4pt"
            },
            "directions": [
                null,
                "-|"
            ]
        },
        {
            "type": "wire",
            "points": [
                {
                    "x": 368.504,
                    "y": -113.386
                },
                {
                    "x": 368.504,
                    "y": 18.898
                },
                {
                    "x": 982.677,
                    "y": 18.898
                }
            ],
            "stroke": {
                "width": "0.4pt"
            },
            "directions": [
                "|-",
                "|-"
            ]
        },
        {
            "type": "wire",
            "points": [
                {
                    "x": 188.976,
                    "y": -113.386
                },
                {
                    "x": -604.724,
                    "y": -75.591
                }
            ],
            "stroke": {
                "width": "0.4pt"
            },
            "directions": [
                "|-"
            ]
        },
        {
            "type": "wire",
            "points": [
                {
                    "x": 623.622,
                    "y": -869.291
                },
                {
                    "x": 623.622,
                    "y": -907.087
                },
                {
                    "x": 623.622,
                    "y": -907.087
                },
                {
                    "x": 623.622,
                    "y": -1096.063
                },
                {
                    "x": 982.677,
                    "y": -1096.063
                }
            ],
            "stroke": {
                "width": "0.4pt"
            },
            "directions": [
                null,
                null,
                null,
                "-|"
            ]
        },
        {
            "type": "wire",
            "points": [
                {
                    "x": 642.52,
                    "y": -869.291
                },
                {
                    "x": 642.52,
                    "y": -907.087
                },
                {
                    "x": 642.52,
                    "y": -907.087
                },
                {
                    "x": 642.52,
                    "y": -1058.268
                },
                {
                    "x": 982.677,
                    "y": -1058.268
                }
            ],
            "stroke": {
                "width": "0.4pt"
            },
            "directions": [
                null,
                null,
                null,
                "-|"
            ]
        },
        {
            "type": "wire",
            "points": [
                {
                    "x": 604.724,
                    "y": -963.78
                },
                {
                    "x": 604.724,
                    "y": -869.291
                }
            ],
            "stroke": {
                "width": "0.4pt"
            },
            "directions": [
                "|-"
            ]
        },
        {
            "type": "wire",
            "points": [
                {
                    "x": 396.85,
                    "y": -869.291
                },
                {
                    "x": 982.677,
                    "y": -1133.858
                }
            ],
            "stroke": {
                "width": "0.4pt"
            },
            "directions": [
                "|-"
            ]
        },
        {
            "type": "rect",
            "position": {
                "x": -661.417,
                "y": -1133.858
            },
            "stroke": {
                "opacity": 0
            },
            "size": {
                "x": 113.386,
                "y": 37.795
            },
            "text": {
                "text": "in_pins_i",
                "align": 2,
                "justify": 0,
                "showPlaceholderText": true
            }
        },
        {
            "type": "rect",
            "position": {
                "x": -661.417,
                "y": -283.465
            },
            "stroke": {
                "opacity": 0
            },
            "size": {
                "x": 113.386,
                "y": 37.795
            },
            "text": {
                "text": "rx_i",
                "align": 2,
                "justify": 0,
                "fontSize": "large",
                "showPlaceholderText": true
            }
        },
        {
            "type": "rect",
            "position": {
                "x": -661.417,
                "y": -75.591
            },
            "stroke": {
                "opacity": 0
            },
            "size": {
                "x": 113.386,
                "y": 37.795
            },
            "text": {
                "text": "p_programm_i",
                "align": 2,
                "justify": 0,
                "fontSize": "large",
                "showPlaceholderText": true
            }
        },
        {
            "type": "rect",
            "position": {
                "x": 1058.268,
                "y": -1133.858
            },
            "stroke": {
                "opacity": 0
            },
            "size": {
                "x": 151.181,
                "y": 37.795
            },
            "text": {
                "text": "next_data_strb_o",
                "justify": 0,
                "fontSize": "large",
                "showPlaceholderText": true
            }
        },
        {
            "type": "rect",
            "position": {
                "x": 1058.268,
                "y": -1096.063
            },
            "stroke": {
                "opacity": 0
            },
            "size": {
                "x": 151.181,
                "y": 37.795
            },
            "text": {
                "text": "out_pins_o",
                "justify": 0,
                "fontSize": "large",
                "showPlaceholderText": true
            }
        },
        {
            "type": "rect",
            "position": {
                "x": 1058.268,
                "y": -1058.268
            },
            "stroke": {
                "opacity": 0
            },
            "size": {
                "x": 151.181,
                "y": 37.795
            },
            "text": {
                "text": "data_valid_strb_o",
                "justify": 0,
                "fontSize": "large",
                "showPlaceholderText": true
            }
        },
        {
            "type": "wire",
            "points": [
                {
                    "x": 822.047,
                    "y": -1086.614
                },
                {
                    "x": 840.945,
                    "y": -1105.512
                }
            ],
            "stroke": {
                "width": "0.4pt"
            },
            "directions": [
                "--"
            ]
        },
        {
            "type": "rect",
            "position": {
                "x": 831.496,
                "y": -1114.961
            },
            "stroke": {
                "opacity": 0
            },
            "size": {
                "x": 37.795,
                "y": 37.795
            },
            "text": {
                "text": "4",
                "align": 2,
                "justify": 0,
                "showPlaceholderText": true
            }
        },
        {
            "type": "rect",
            "position": {
                "x": 425.197,
                "y": -850.394
            },
            "stroke": {
                "color": "rgb(192,192,192)",
                "style": "denselydashed"
            },
            "size": {
                "x": 472.441,
                "y": 37.795
            },
            "text": {
                "text": "I/O Interface",
                "align": 1,
                "justify": 0,
                "fontSize": "Large"
            }
        },
        {
            "type": "rect",
            "position": {
                "x": 207.874,
                "y": -732.283
            },
            "stroke": {
                "color": "rgb(192,192,192)",
                "style": "denselydashed"
            },
            "size": {
                "x": 113.386,
                "y": 179.527
            },
            "text": {
                "text": "Memory\nInterface",
                "align": 1,
                "justify": 0,
                "fontSize": "Large"
            }
        },
        {
            "type": "rect",
            "position": {
                "x": 207.874,
                "y": -500.787
            },
            "stroke": {
                "color": "rgb(192,192,192)",
                "style": "denselydashed"
            },
            "size": {
                "x": 113.386,
                "y": 207.874
            },
            "text": {
                "text": "ALU\nInterface",
                "align": 1,
                "justify": 0,
                "fontSize": "Large"
            }
        },
        {
            "type": "rect",
            "position": {
                "x": 207.874,
                "y": -226.772
            },
            "stroke": {
                "color": "rgb(192,192,192)",
                "style": "denselydashed"
            },
            "size": {
                "x": 113.386,
                "y": 226.772
            },
            "text": {
                "text": "Programmer\nInterface",
                "align": 1,
                "justify": 0,
                "fontSize": "Large"
            }
        },
        {
            "type": "rect",
            "position": {
                "x": 661.417,
                "y": -467.717
            },
            "stroke": {
                "color": "rgb(192,192,192)",
                "style": "denselydashed"
            },
            "size": {
                "x": 113.386,
                "y": 708.661
            },
            "text": {
                "text": "Register\nInterface",
                "align": 1,
                "justify": 0,
                "fontSize": "Large"
            }
        },
        {
            "type": "rect",
            "position": {
                "x": 415.748,
                "y": -151.181
            },
            "stroke": {
                "color": "rgb(192,192,192)",
                "style": "denselydashed"
            },
            "size": {
                "x": 226.772,
                "y": 75.591
            },
            "text": {
                "text": "Debug\nInterface",
                "align": 1,
                "justify": 0,
                "fontSize": "Large"
            }
        },
        {
            "type": "rect",
            "position": {
                "x": 1077.165,
                "y": -75.591
            },
            "stroke": {
                "opacity": 0
            },
            "size": {
                "x": 188.976,
                "y": 37.795
            },
            "text": {
                "text": "programm_o",
                "justify": 0,
                "fontSize": "large",
                "showPlaceholderText": true
            }
        },
        {
            "type": "rect",
            "position": {
                "x": 1077.165,
                "y": -56.693
            },
            "stroke": {
                "opacity": 0
            },
            "size": {
                "x": 188.976,
                "y": 37.795
            },
            "text": {
                "text": "fetch_instr_o",
                "justify": 0,
                "fontSize": "large",
                "showPlaceholderText": true
            }
        },
        {
            "type": "rect",
            "position": {
                "x": 1077.165,
                "y": -37.795
            },
            "stroke": {
                "opacity": 0
            },
            "size": {
                "x": 188.976,
                "y": 37.795
            },
            "text": {
                "text": "decode_o",
                "justify": 0,
                "fontSize": "large",
                "showPlaceholderText": true
            }
        },
        {
            "type": "rect",
            "position": {
                "x": 1077.165,
                "y": -18.898
            },
            "stroke": {
                "opacity": 0
            },
            "size": {
                "x": 188.976,
                "y": 37.795
            },
            "text": {
                "text": "fetch_op_o",
                "justify": 0,
                "fontSize": "large",
                "showPlaceholderText": true
            }
        },
        {
            "type": "rect",
            "position": {
                "x": 1077.165,
                "y": 0
            },
            "stroke": {
                "opacity": 0
            },
            "size": {
                "x": 188.976,
                "y": 37.795
            },
            "text": {
                "text": "fetch_mdr_o",
                "justify": 0,
                "fontSize": "large",
                "showPlaceholderText": true
            }
        },
        {
            "type": "rect",
            "position": {
                "x": 1077.165,
                "y": 18.898
            },
            "stroke": {
                "opacity": 0
            },
            "size": {
                "x": 188.976,
                "y": 37.795
            },
            "text": {
                "text": "execute_o",
                "justify": 0,
                "fontSize": "large",
                "showPlaceholderText": true
            }
        },
        {
            "type": "group",
            "components": [
                {
                    "type": "wire",
                    "points": [
                        {
                            "x": 103.937,
                            "y": -1124.409
                        },
                        {
                            "x": 122.835,
                            "y": -1143.307
                        }
                    ],
                    "stroke": {
                        "width": "0.4pt"
                    },
                    "directions": [
                        "--"
                    ]
                },
                {
                    "type": "rect",
                    "position": {
                        "x": 113.386,
                        "y": -1152.756
                    },
                    "stroke": {
                        "opacity": 0
                    },
                    "size": {
                        "x": 37.795,
                        "y": 37.795
                    },
                    "text": {
                        "text": "4",
                        "align": 2,
                        "justify": 0,
                        "showPlaceholderText": true
                    }
                }
            ]
        },
        {
            "type": "wire",
            "points": [
                {
                    "x": 907.087,
                    "y": -604.724
                },
                {
                    "x": 982.677,
                    "y": -604.724
                }
            ],
            "stroke": {
                "width": "0.4pt"
            },
            "directions": [
                "-|"
            ]
        },
        {
            "type": "rect",
            "position": {
                "x": 1058.268,
                "y": -604.724
            },
            "stroke": {
                "opacity": 0
            },
            "size": {
                "x": 151.181,
                "y": 37.795
            },
            "text": {
                "text": "instr_reg_o",
                "justify": 0,
                "fontSize": "large",
                "showPlaceholderText": true
            }
        },
        {
            "type": "rect",
            "position": {
                "x": 188.976,
                "y": -1266.142
            },
            "stroke": {
                "opacity": 0
            },
            "size": {
                "x": 340.157,
                "y": 113.386
            },
            "text": {
                "text": "CPU",
                "align": 1,
                "justify": 0,
                "fontSize": "Huge",
                "showPlaceholderText": true
            }
        },
        {
            "type": "rect",
            "position": {
                "x": 434.646,
                "y": -491.339
            },
            "size": {
                "x": 566.929,
                "y": 755.906
            },
            "text": {
                "text": "Control Unit",
                "align": 1,
                "justify": 0,
                "fontSize": "Huge"
            }
        }
    ]
}